<?xml version="1.0" encoding="UTF-8"?>
<!DOCTYPE mapper PUBLIC "-//mybatis.org//DTD Mapper 3.0//EN" "http://mybatis.org/dtd/mybatis-3-mapper.dtd">
<mapper namespace="com.kaibutsusama.stock.system.dao.TTradeAccountMapper">
  <resultMap id="BaseResultMap" type="com.kaibutsusama.stock.system.entity.TTradeAccount">
    <!--
      WARNING - @mbg.generated
      This element is automatically generated by MyBatis Generator, do not modify.
      This element was generated on Sat Aug 13 19:12:41 CST 2022.
    -->
    <result column="id" jdbcType="BIGINT" property="id" />
    <result column="userId" jdbcType="BIGINT" property="userId" />
    <result column="accountNo" jdbcType="VARCHAR" property="accountNo" />
    <result column="balance" jdbcType="BIGINT" property="balance" />
    <result column="tradeGroupId" jdbcType="BIGINT" property="tradeGroupId" />
    <result column="activeTime" jdbcType="TIMESTAMP" property="activeTime" />
    <result column="status" jdbcType="TINYINT" property="status" />
    <result column="institutionTypeId" jdbcType="VARCHAR" property="institutionTypeId" />
    <result column="institutionId" jdbcType="BIGINT" property="institutionId" />
    <result column="companyId" jdbcType="BIGINT" property="companyId" />
    <result column="userName" jdbcType="VARCHAR" property="userName" />
    <result column="tradeGroupName" jdbcType="VARCHAR" property="tradeGroupName" />
  </resultMap>
  <insert id="insert" parameterType="com.kaibutsusama.stock.system.entity.TTradeAccount">
    <!--
      WARNING - @mbg.generated
      This element is automatically generated by MyBatis Generator, do not modify.
      This element was generated on Sat Aug 13 19:12:41 CST 2022.
    -->
    <selectKey keyProperty="id" order="AFTER" resultType="java.lang.Long">
      SELECT LAST_INSERT_ID()
    </selectKey>
    insert into t_trade_account (userId, accountNo, balance, 
      tradeGroupId, activeTime, status, 
      institutionTypeId, institutionId, companyId, 
      userName, tradeGroupName)
    values (#{userId,jdbcType=BIGINT}, #{accountNo,jdbcType=VARCHAR}, #{balance,jdbcType=BIGINT}, 
      #{tradeGroupId,jdbcType=BIGINT}, #{activeTime,jdbcType=TIMESTAMP}, #{status,jdbcType=TINYINT}, 
      #{institutionTypeId,jdbcType=VARCHAR}, #{institutionId,jdbcType=BIGINT}, #{companyId,jdbcType=BIGINT}, 
      #{userName,jdbcType=VARCHAR}, #{tradeGroupName,jdbcType=VARCHAR})
  </insert>
  <insert id="insertSelective" parameterType="com.kaibutsusama.stock.system.entity.TTradeAccount">
    <!--
      WARNING - @mbg.generated
      This element is automatically generated by MyBatis Generator, do not modify.
      This element was generated on Sat Aug 13 19:12:41 CST 2022.
    -->
    <selectKey keyProperty="id" order="AFTER" resultType="java.lang.Long">
      SELECT LAST_INSERT_ID()
    </selectKey>
    insert into t_trade_account
    <trim prefix="(" suffix=")" suffixOverrides=",">
      <if test="userId != null">
        userId,
      </if>
      <if test="accountNo != null">
        accountNo,
      </if>
      <if test="balance != null">
        balance,
      </if>
      <if test="tradeGroupId != null">
        tradeGroupId,
      </if>
      <if test="activeTime != null">
        activeTime,
      </if>
      <if test="status != null">
        status,
      </if>
      <if test="institutionTypeId != null">
        institutionTypeId,
      </if>
      <if test="institutionId != null">
        institutionId,
      </if>
      <if test="companyId != null">
        companyId,
      </if>
      <if test="userName != null">
        userName,
      </if>
      <if test="tradeGroupName != null">
        tradeGroupName,
      </if>
    </trim>
    <trim prefix="values (" suffix=")" suffixOverrides=",">
      <if test="userId != null">
        #{userId,jdbcType=BIGINT},
      </if>
      <if test="accountNo != null">
        #{accountNo,jdbcType=VARCHAR},
      </if>
      <if test="balance != null">
        #{balance,jdbcType=BIGINT},
      </if>
      <if test="tradeGroupId != null">
        #{tradeGroupId,jdbcType=BIGINT},
      </if>
      <if test="activeTime != null">
        #{activeTime,jdbcType=TIMESTAMP},
      </if>
      <if test="status != null">
        #{status,jdbcType=TINYINT},
      </if>
      <if test="institutionTypeId != null">
        #{institutionTypeId,jdbcType=VARCHAR},
      </if>
      <if test="institutionId != null">
        #{institutionId,jdbcType=BIGINT},
      </if>
      <if test="companyId != null">
        #{companyId,jdbcType=BIGINT},
      </if>
      <if test="userName != null">
        #{userName,jdbcType=VARCHAR},
      </if>
      <if test="tradeGroupName != null">
        #{tradeGroupName,jdbcType=VARCHAR},
      </if>
    </trim>
  </insert>
</mapper>